topicwizard/__init__.py
topicwizard/app.py
topicwizard/assets/favicon.ico
topicwizard/blueprints/__init__.py
topicwizard/blueprints/app.py
topicwizard/blueprints/documents.py
topicwizard/blueprints/groups.py
topicwizard/blueprints/template.py
topicwizard/blueprints/topics.py
topicwizard/blueprints/words.py
topicwizard/compatibility/__init__.py
topicwizard/compatibility/bertopic.py
topicwizard/compatibility/gensim.py
topicwizard/components/__init__.py
topicwizard/components/color_legend.py
topicwizard/components/documents/__init__.py
topicwizard/components/documents/document_bar.py
topicwizard/components/documents/document_map.py
topicwizard/components/documents/document_pie.py
topicwizard/components/documents/document_selector.py
topicwizard/components/documents/document_timeline.py
topicwizard/components/documents/document_viewer.py
topicwizard/components/documents/document_wordcloud.py
topicwizard/components/documents/window_slider.py
topicwizard/components/groups/group_barplot.py
topicwizard/components/groups/group_map.py
topicwizard/components/groups/group_wordcloud.py
topicwizard/components/topics/__init__.py
topicwizard/components/topics/intertopic_map.py
topicwizard/components/topics/relevance_slider.py
topicwizard/components/topics/topic_barplot.py
topicwizard/components/topics/topic_namer.py
topicwizard/components/topics/topic_switcher.py
topicwizard/components/topics/wordcloud.py
topicwizard/components/words/__init__.py
topicwizard/components/words/association_slider.py
topicwizard/components/words/word_barplot.py
topicwizard/components/words/word_map.py
topicwizard/components/words/word_selector.py
topicwizard/data.py
topicwizard/deployment.py
topicwizard/figures/__init__.py
topicwizard/figures/documents.py
topicwizard/figures/groups.py
topicwizard/figures/topics.py
topicwizard/figures/words.py
topicwizard/help/documents.py
topicwizard/help/groups.py
topicwizard/help/topics.py
topicwizard/help/utils.py
topicwizard/help/words.py
topic_wizard-1.1.4.dist-info/LICENSE
topic_wizard-1.1.4.dist-info/METADATA
topic_wizard-1.1.4.dist-info/WHEEL
topic_wizard-1.1.4.dist-info/RECORD
