Metadata-Version: 2.1
Name: topic-wizard
Version: 1.1.4
Summary: Pretty and opinionated topic model visualization in Python.
License: MIT
Author: Márton Kardos
Author-email: power.up1163@gmail.com
Requires-Python: >=3.8.0
Classifier: License :: OSI Approved :: MIT License
Classifier: Programming Language :: Python :: 3
Classifier: Programming Language :: Python :: 3.8
Classifier: Programming Language :: Python :: 3.9
Classifier: Programming Language :: Python :: 3.10
Classifier: Programming Language :: Python :: 3.11
Classifier: Programming Language :: Python :: 3.12
Requires-Dist: Pillow (>=10.1.0,<11.0.0)
Requires-Dist: dash (>=2.7.1,<3.0.0)
Requires-Dist: dash-extensions (>=1.0.4,<2.0.0)
Requires-Dist: dash-iconify (>=0.1.2,<0.2.0)
Requires-Dist: dash-mantine-components (>=0.12.1,<0.13.0)
Requires-Dist: joblib (>=1.2.0,<2.0.0)
Requires-Dist: numpy (>=1.22.0)
Requires-Dist: pandas (>=1.5.2)
Requires-Dist: scikit-learn (>=1.2.0,<2.0.0)
Requires-Dist: scipy (>=1.8.0)
Requires-Dist: umap-learn (>=0.5.3)
Requires-Dist: wordcloud (>=1.9.2,<2.0.0)
